[
  {
    "name": "Silvarya",
    "language": "TR/EN",
    "players": 0,
    "ping": "163.37",
    "location": "CH/EU",
    "status": "Online",
    "website": "www.silvarya.com.tr",
    "description": "this is a private server",
    "colour": "white",
    "type": "Deathmatch"
  },
  {
    "name": "Silvarya",
    "language": "TR/EN",
    "players": 0,
    "ping": "158.09",
    "location": "CH/EU",
    "status": "Online",
    "website": "www.silvarya.com.tr",
    "description": "this is a private server",
    "colour": "white",
    "type": "Deathmatch"
  },
  {
    "name": "Silvarya",
    "language": "TR/EN",
    "players": 0,
    "ping": "153.31",
    "location": "CH/EU",
    "status": "Online",
    "website": "www.silvarya.com.tr",
    "description": "this is a private server",
    "colour": "white",
    "type": "Deathmatch"
  },
  {
    "name": "Silvarya",
    "language": "TR/EN",
    "players": 0,
    "ping": "85.87",
    "location": "CH/EU",
    "status": "Online",
    "website": "www.silvarya.com.tr",
    "description": "this is a private server",
    "colour": "white",
    "type": "Deathmatch"
  },
  {
    "name": "Silvarya",
    "language": "TR/EN",
    "players": 0,
    "ping": "177.66",
    "location": "CH/EU",
    "status": "Online",
    "website": "www.silvarya.com.tr",
    "description": "this is a private server",
    "colour": "white",
    "type": "Deathmatch"
  }
]