[
  {
    "name": "Silvarya",
    "language": "TR/EN",
    "players": 0,
    "ping": "61.77",
    "location": "CH/EU",
    "status": "Online",
    "website": "www.silvarya.com.tr",
    "description": "this is a private server",
    "colour": "white",
    "type": "Deathmatch"
  },
  {
    "name": "Silvarya",
    "language": "TR/EN",
    "players": 0,
    "ping": "59.09",
    "location": "CH/EU",
    "status": "Online",
    "website": "www.silvarya.com.tr",
    "description": "this is a private server",
    "colour": "white",
    "type": "Deathmatch"
  },
  {
    "name": "Silvarya",
    "language": "TR/EN",
    "players": 0,
    "ping": "95.13",
    "location": "CH/EU",
    "status": "Online",
    "website": "www.silvarya.com.tr",
    "description": "this is a private server",
    "colour": "white",
    "type": "Deathmatch"
  },
  {
    "name": "Silvarya",
    "language": "TR/EN",
    "players": 0,
    "ping": "117.94",
    "location": "CH/EU",
    "status": "Online",
    "website": "www.silvarya.com.tr",
    "description": "this is a private server",
    "colour": "white",
    "type": "Deathmatch"
  },
  {
    "name": "Silvarya",
    "language": "TR/EN",
    "players": 0,
    "ping": "168.02",
    "location": "CH/EU",
    "status": "Online",
    "website": "www.silvarya.com.tr",
    "description": "this is a private server",
    "colour": "white",
    "type": "Deathmatch"
  },
  {
    "name": "Silvarya",
    "language": "TR/EN",
    "players": 0,
    "ping": "124.82",
    "location": "CH/EU",
    "status": "Online",
    "website": "www.silvarya.com.tr",
    "description": "this is a private server",
    "colour": "white",
    "type": "Deathmatch"
  }
]